{
    "edit_cursor_values": {
        "text": "You can click X or Y value in the cursor panel and type an exact value to move the cursor to.",
        "image": "edit_cursor_values.gif"
    },
    "disable_start_window": {
        "text": "You can disable this start window using the respective flag in the application settings dialog."
    },
    "enlarge_tip_preview": {
        "text": "You can enlarge these small preview images by clicking them. Also, some of them are animated! →",
        "preview": "enlarge_tip_preview.png",
        "image": "enlarge_tip_preview.gif"
    }
}
